vercel_mgmt/__init__.py
vercel_mgmt/mgmt.py
vercel_mgmt/vercel.py
vercel_mgmt-0.1.5.dist-info/WHEEL
vercel_mgmt-0.1.5.dist-info/entry_points.txt
vercel_mgmt-0.1.5.dist-info/METADATA
vercel_mgmt-0.1.5.dist-info/RECORD
